[{"Name": "Tutorial", "Path": "<a href=\"projects/Tutorial\" target=\"_blank\">projects/Tutorial</a>", "Link": "<a href=\"projects/Tutorial/Tutorial.ipynb\" target=\"_blank\">Notebook</a>", "Creation Time": "Thu May 16 03:29:56 2019", "_path": "projects/Tutorial", "_tool": "projects/Tutorial/Tutorial.ipynb"}, {"Name": "TMD Example", "Path": "<a href=\"projects/TMD Example\" target=\"_blank\">projects/TMD Example</a>", "Link": "<a href=\"projects/TMD Example/TMD Example.ipynb\" target=\"_blank\">Notebook</a>", "Creation Time": "Wed Jul 10 13:42:48 2019", "_path": "projects/TMD Example", "_tool": "projects/TMD Example/TMD Example.ipynb"}]